{
  "scanId": "scan-1784309907649",
  "generatedAt": "2026-07-17T17:38:27.649Z",
  "source": "txline-dev",
  "market": "1X2 full match",
  "matches": 1,
  "flagged": 0,
  "audits": [
    {
      "fixtureId": 18257865,
      "competition": "World Cup",
      "home": "France",
      "away": "England",
      "status": "pre",
      "kickoff": 1784408400000,
      "quoted": [
        1.99,
        4.13,
        3.91
      ],
      "fairProb": [
        0.5023,
        0.242,
        0.2556
      ],
      "fairLine": [
        1.99,
        4.13,
        3.91
      ],
      "overround": -0.0001,
      "ticks": 1,
      "lastTickTs": 1784309824725,
      "moveZ": 0,
      "integrity": 100,
      "verdict": "CLEAN",
      "anomalies": []
    }
  ]
}
