{"scanId":"scan-1783768777258","generatedAt":"2026-07-11T11:19:37.258Z","source":"txline-dev","market":"1X2 full match","matches":2,"flagged":0,"audits":[{"fixtureId":18213979,"competition":"World Cup","home":"Norway","away":"England","status":"pre","kickoff":1783803600000,"quoted":[4.04,3.92,2.01],"fairProb":[0.2475,0.2553,0.4972],"fairLine":[4.04,3.92,2.01],"overround":0.0001,"ticks":1,"lastTickTs":1783768604163,"moveZ":0,"integrity":100,"verdict":"CLEAN","anomalies":[]},{"fixtureId":18222446,"competition":"World Cup","home":"Argentina","away":"Switzerland","status":"pre","kickoff":1783818000000,"quoted":[1.76,3.78,6.02],"fairProb":[0.5691,0.2647,0.1662],"fairLine":[1.76,3.78,6.02],"overround":0.0001,"ticks":1,"lastTickTs":1783768762954,"moveZ":0,"integrity":100,"verdict":"CLEAN","anomalies":[]}]}